prod_monitoring_nsxt/__init__.py
prod_monitoring_nsxt/nodes/__init__.py
prod_monitoring_nsxt/nodes/node_nsxt_edge_metrics.py
prod_monitoring_nsxt/nodes/node_nsxt_manager_metrics.py
prod_monitoring_nsxt-1.0.3.post2.dist-info/LICENSE.md
prod_monitoring_nsxt-1.0.3.post2.dist-info/METADATA
prod_monitoring_nsxt-1.0.3.post2.dist-info/WHEEL
prod_monitoring_nsxt-1.0.3.post2.dist-info/entry_points.txt
prod_monitoring_nsxt-1.0.3.post2.dist-info/top_level.txt
prod_monitoring_nsxt-1.0.3.post2.dist-info/RECORD
