Metadata-Version: 2.1
Name: prod-monitoring-nsxt
Version: 1.0.3.post2
Summary: Implements nodes for remote monitoring of NSX-T devices.
Home-page: UNKNOWN
Author: The_Crazy_Sys_Admin
License: UNKNOWN
Platform: UNKNOWN
Requires-Python: >=3.6.8, <4
License-File: LICENSE.md
Requires-Dist: library-nsxt (<2,>=1.0.8)
Requires-Dist: proc-monitoring (<2,>=1.0.1)
